textoverlay/__init__.py
textoverlay/models/__init__.py
textoverlay/models/advanced_layout.py
textoverlay/models/model_downloader.py
textoverlay/models/saliency.pt
textoverlay/models/u2net.py
textoverlay/overlay/interactive_overlay.py
textoverlay/overlay/layout.py
textoverlay/overlay/run_overlay.py
textoverlay/utils/font_manager.py
textoverlay/utils/render.py
textoverlay/utils/vision.py
textoverlay-0.1.0.dist-info/licenses/LICENSE
textoverlay-0.1.0.dist-info/METADATA
textoverlay-0.1.0.dist-info/WHEEL
textoverlay-0.1.0.dist-info/top_level.txt
textoverlay-0.1.0.dist-info/RECORD
