Metadata-Version: 2.4
Name: textoverlay
Version: 0.1.0
Summary: A Python package for adding text overlays to images with the power of Computer Vision
Author-email: Yug Makhecha <yugmakhecha1710@gmail.com>
Project-URL: Homepage, https://github.com/YugMakhecha17/textoverlay
Project-URL: Source, https://github.com/YugMakhecha17/textoverlay
Project-URL: Bug Reports, https://github.com/YugMakhecha17/textoverlay/issues
Keywords: text,overlay,image,AI,graphics
Classifier: Development Status :: 3 - Alpha
Classifier: Intended Audience :: Developers
Classifier: Programming Language :: Python :: 3
Classifier: Topic :: Multimedia :: Graphics
Requires-Python: >=3.8
License-File: LICENSE
Requires-Dist: Pillow>=8.0.0
Requires-Dist: numpy>=1.20.0
Requires-Dist: torch>=1.9.0
Requires-Dist: transformers>=4.0.0
Requires-Dist: opencv-python>=4.5.0
Requires-Dist: requests>=2.25.0
Dynamic: license-file
